greatbrowser/__init__.py
greatbrowser/functions.py
greatbrowser/main.py
greatbrowser-1.1.6.dist-info/LICENSE
greatbrowser-1.1.6.dist-info/METADATA
greatbrowser-1.1.6.dist-info/WHEEL
greatbrowser-1.1.6.dist-info/top_level.txt
greatbrowser-1.1.6.dist-info/RECORD
