Metadata-Version: 2.1
Name: greatbrowser
Version: 1.1.6
Summary: Automate Stanford's GREAT browser
Author: Samuel D. Anderson
Author-email: sanderson01@wesleyan.edu
Project-URL: Source, https://github.com/SamAndTheSun/greatbrowser
Project-URL: Bug Reports, https://github.com/SamAndTheSun/greatbrowser/issues
Keywords: python,genomics,genetics,greatbrowser,great,automated,analysis
Classifier: Intended Audience :: Science/Research
Classifier: Programming Language :: Python :: 3
Classifier: Operating System :: MacOS :: MacOS X
Classifier: Operating System :: Microsoft :: Windows
Classifier: Operating System :: Unix
License-File: LICENSE
Requires-Dist: selenium
Requires-Dist: beautifulsoup4
Requires-Dist: requests
Requires-Dist: webdriver-manager
Requires-Dist: pandas
Requires-Dist: polars
Requires-Dist: numpy
Requires-Dist: Pillow
Requires-Dist: urllib3
Requires-Dist: lxml
